s11auth/__init__.py
s11auth/cgi.py
s11auth/loading.py
s11auth/plugin.py
openstack_s11auth-1.0.3.dist-info/METADATA
openstack_s11auth-1.0.3.dist-info/WHEEL
openstack_s11auth-1.0.3.dist-info/entry_points.txt
openstack_s11auth-1.0.3.dist-info/pbr.json
openstack_s11auth-1.0.3.dist-info/top_level.txt
openstack_s11auth-1.0.3.dist-info/RECORD
