Metadata-Version: 2.1
Name: openstack-s11auth
Version: 1.0.3
Summary: Openstack client middleware for authenticating with s11
Requires-Python: >=3.6
Requires-Dist: pbr>=6.0.0
Requires-Dist: six>=1.10.0
Requires-Dist: positional>=1.1.1
Requires-Dist: keystoneauth1>=2.10.0
Requires-Dist: pkce>=1.0
